outpack_query_parser-0.3.0.dist-info/METADATA
outpack_query_parser-0.3.0.dist-info/WHEEL
outpack_query_parser-0.3.0.dist-info/license_files/LICENSE
outpack_query_parser/__init__.py
outpack_query_parser/outpack_query_parser.abi3.so
outpack_query_parser-0.3.0.dist-info/RECORD
