Metadata-Version: 2.1
Name: outpack_query_parser
Version: 0.3.0
License-File: LICENSE
